snap_tracker/__init__.py
snap_tracker/__main__.py
snap_tracker/debug.py
snap_tracker/helpers.py
snap_tracker/split_rates.py
snap_tracker/types.py
tests/test_splitrates.py
snap_tracker-0.1.1.dist-info/METADATA
snap_tracker-0.1.1.dist-info/WHEEL
snap_tracker-0.1.1.dist-info/entry_points.txt
snap_tracker-0.1.1.dist-info/top_level.txt
snap_tracker-0.1.1.dist-info/RECORD
