Metadata-Version: 2.1
Name: snap-tracker
Version: 0.1.1
Summary: Collection and game tracker for Marvel Snap. Work in progress.
Author-email: Kimmo Parviainen-Jalanko <kimvais@kimva.is>
License: MIT License
Project-URL: Homepage, https://github.com/kimvais/snap-tracker/
Project-URL: Repository, https://github.com/kimvais/snap-tracker.git
Project-URL: Issues, https://github.com/kimvais/snap-tracker/issues
Keywords: Marvel Snap
Classifier: Development Status :: 3 - Alpha
Classifier: Environment :: Console
Classifier: Operating System :: Microsoft :: Windows
Classifier: Topic :: Games/Entertainment
Classifier: Topic :: Utilities
Requires-Python: >=3.12
Requires-Dist: aiofiles
Requires-Dist: fire
Requires-Dist: motor
Requires-Dist: rich
Requires-Dist: stringcase
Requires-Dist: watchfiles
Provides-Extra: dev
Requires-Dist: ipython ; extra == 'dev'
Requires-Dist: pytest ; extra == 'dev'
Requires-Dist: ruff ; extra == 'dev'
